bookmaker/BookMaker.py
bookmaker/XMLforEPUB.py
bookmaker/__init__.py
bookmaker/about.py
bookmaker/book_resources/README.md
bookmaker/book_resources/SUMMARY.md
bookmaker/com.marcrisoft.bookmaker.gschema.xml
bookmaker/css_resources/__init__.py
bookmaker/css_resources/github-markdown.css
bookmaker/css_resources/github-pygments.css
bookmaker/css_resources/pdf-styles.css
bookmaker/derivation.py
bookmaker/gschemas.compiled
bookmaker/logo.svg
bookmaker/markdown_view.py
bookmaker/mermaid.min.js
bookmaker/my_extra.py
bookmaker/my_footnotes.py
bookmaker/my_table.py
bookmaker/pre_view.py
bookmaker/sync_scroll.py
bookmaker/toc_utils.py
bookmaker/toc_view.py
bookmaker/ui_menu.xml
bookmaker/ui_statusbar.xml
bookmaker/ui_toolbar.xml
bookmaker_mc-0.6.0.dist-info/entry_points.txt
bookmaker_mc-0.6.0.dist-info/LICENSE.txt
bookmaker_mc-0.6.0.dist-info/WHEEL
bookmaker_mc-0.6.0.dist-info/METADATA
bookmaker_mc-0.6.0.dist-info/RECORD
