Metadata-Version: 2.1
Name: bookmaker-mc
Version: 0.6.0
Summary: A Book Authoring Application in Python
Home-page: https://github.com/marcris/bookmaker-mc
License: MIT
Author: Chris Brown
Author-email: chris@marcrisoft.co.uk
Requires-Python: >=3.8,<4.0
Classifier: Development Status :: 4 - Beta
Classifier: Intended Audience :: End Users/Desktop
Classifier: License :: OSI Approved :: MIT License
Classifier: Programming Language :: Python :: 3
Classifier: Programming Language :: Python :: 3.10
Classifier: Programming Language :: Python :: 3.8
Classifier: Programming Language :: Python :: 3.9
Requires-Dist: PyGObject (>=3.40,<4.0)
Requires-Dist: Pygments (>=2.9,<3.0)
Requires-Dist: mistune (>=2.0.0rc1,<3.0.0)
Requires-Dist: tomli (>=2.0.1,<3.0.0)
Project-URL: Repository, https://github.com/marcris/bookmaker-mc
